tensap/__init__.py
tensap/approximation/__init__.py
tensap/approximation/bases/__init__.py
tensap/approximation/bases/full_tensor_product_functional_basis.py
tensap/approximation/bases/functional_bases.py
tensap/approximation/bases/functional_basis.py
tensap/approximation/bases/functional_basis_array.py
tensap/approximation/bases/polynomial_functional_basis.py
tensap/approximation/bases/sparse_tensor_product_functional_basis.py
tensap/approximation/bases/sub_functional_basis.py
tensap/approximation/bases/user_defined_functional_basis.py
tensap/approximation/integration/__init__.py
tensap/approximation/integration/integration_rules.py
tensap/approximation/learning/__init__.py
tensap/approximation/learning/learning.py
tensap/approximation/learning/linear_model_learning.py
tensap/approximation/learning/linear_model_learning_custom_loss.py
tensap/approximation/learning/linear_model_learning_density_l2.py
tensap/approximation/learning/linear_model_learning_square_loss.py
tensap/approximation/learning/loss_functions.py
tensap/approximation/tensor_approximation/__init__.py
tensap/approximation/tensor_approximation/principal_component_analysis/__init__.py
tensap/approximation/tensor_approximation/principal_component_analysis/functional_tensor_principal_component_analysis.py
tensap/approximation/tensor_approximation/principal_component_analysis/tensor_principal_component_analysis.py
tensap/approximation/tensor_approximation/tensor_learning/__init__.py
tensap/approximation/tensor_approximation/tensor_learning/canonical_tensor_learning.py
tensap/approximation/tensor_approximation/tensor_learning/tensor_learning.py
tensap/approximation/tensor_approximation/tensor_learning/tree_based_tensor_learning.py
tensap/approximation/tools/__init__.py
tensap/approximation/tools/model_selection.py
tensap/functions/__init__.py
tensap/functions/compositional_model_function.py
tensap/functions/function.py
tensap/functions/functional_tensor.py
tensap-1.1.dist-info/DESCRIPTION.rst
tensap-1.1.dist-info/METADATA
tensap-1.1.dist-info/RECORD
tensap-1.1.dist-info/WHEEL
tensap-1.1.dist-info/metadata.json
tensap-1.1.dist-info/top_level.txt
