Metadata-Version: 2.0
Name: tensap
Version: 1.1
Summary: Tensor Approximation Package: a Python package for the approximation of functions and tensors.
Home-page: https://anthony-nouy.github.io/tensap/
Author: Anthony Nouy, Erwan Grelier
Author-email: anthony.nouy@ec-nantes.fr
License: UNKNOWN
Platform: UNKNOWN
Classifier: Programming Language :: Python :: 3
Classifier: License :: OSI Approved :: GNU Lesser General Public License v3 or later (LGPLv3+)
Classifier: Operating System :: OS Independent
Requires-Python: >=3.6
Requires-Dist: numpy
Requires-Dist: scipy
